build_scripts/installer-version.py
chia/__init__.py
chia/py.typed
chia/pyinstaller.spec
chia/clvm/singleton.py
chia/clvm/spend_sim.py
chia/cmds/__init__.py
chia/cmds/chia.py
chia/cmds/configure.py
chia/cmds/farm.py
chia/cmds/farm_funcs.py
chia/cmds/init.py
chia/cmds/init_funcs.py
chia/cmds/keys.py
chia/cmds/keys_funcs.py
chia/cmds/netspace.py
chia/cmds/netspace_funcs.py
chia/cmds/passphrase.py
chia/cmds/passphrase_funcs.py
chia/cmds/plotnft.py
chia/cmds/plotnft_funcs.py
chia/cmds/plots.py
chia/cmds/plotters.py
chia/cmds/show.py
chia/cmds/start.py
chia/cmds/start_funcs.py
chia/cmds/stop.py
chia/cmds/units.py
chia/cmds/wallet.py
chia/cmds/wallet_funcs.py
chia/consensus/__init__.py
chia/consensus/block_body_validation.py
chia/consensus/block_creation.py
chia/consensus/block_header_validation.py
chia/consensus/block_record.py
chia/consensus/block_rewards.py
chia/consensus/block_root_validation.py
chia/consensus/blockchain.py
chia/consensus/blockchain_interface.py
chia/consensus/coinbase.py
chia/consensus/condition_costs.py
chia/consensus/constants.py
chia/consensus/cost_calculator.py
chia/consensus/default_constants.py
chia/consensus/deficit.py
chia/consensus/difficulty_adjustment.py
chia/consensus/find_fork_point.py
chia/consensus/full_block_to_block_record.py
chia/consensus/get_block_challenge.py
chia/consensus/make_sub_epoch_summary.py
chia/consensus/multiprocess_validation.py
chia/consensus/network_type.py
chia/consensus/pos_quality.py
chia/consensus/pot_iterations.py
chia/consensus/vdf_info_computation.py
chia/daemon/__init__.py
chia/daemon/client.py
chia/daemon/keychain_proxy.py
chia/daemon/keychain_server.py
chia/daemon/server.py
chia/daemon/windows_signal.py
chia/farmer/__init__.py
chia/farmer/farmer.py
chia/farmer/farmer_api.py
chia/full_node/__init__.py
chia/full_node/block_store.py
chia/full_node/bundle_tools.py
chia/full_node/coin_store.py
chia/full_node/full_node.py
chia/full_node/full_node_api.py
chia/full_node/full_node_store.py
kiwi_blockchain-1.0.3.dist-info/LICENSE
kiwi_blockchain-1.0.3.dist-info/METADATA
kiwi_blockchain-1.0.3.dist-info/WHEEL
kiwi_blockchain-1.0.3.dist-info/entry_points.txt
kiwi_blockchain-1.0.3.dist-info/top_level.txt
kiwi_blockchain-1.0.3.dist-info/RECORD
