Metadata-Version: 2.1
Name: kiwi-blockchain
Version: 1.0.3
Summary: Kiwi blockchain full node, farmer, timelord, and wallet.
Home-page: https://kiwihealthcare.network/
Author: KIWI NETWORK
Author-email: kiwihealthcare888@gmail.com
License: Apache License
Keywords: kiwi blockchain node
Requires-Python: >=3.7, <4
License-File: LICENSE
Requires-Dist: multidict (==5.1.0)
Requires-Dist: blspy (==1.0.6)
Requires-Dist: chiavdf (==1.0.3)
Requires-Dist: chiabip158 (==1.0)
Requires-Dist: chiapos (==1.0.6)
Requires-Dist: clvm (==0.9.7)
Requires-Dist: clvm-rs (==0.1.15)
Requires-Dist: clvm-tools (==0.4.3)
Requires-Dist: aiohttp (==3.7.4)
Requires-Dist: aiosqlite (==0.17.0)
Requires-Dist: bitstring (==3.1.9)
Requires-Dist: colorama (==0.4.4)
Requires-Dist: colorlog (==5.0.1)
Requires-Dist: concurrent-log-handler (==0.9.19)
Requires-Dist: cryptography (==3.4.7)
Requires-Dist: fasteners (==0.16.3)
Requires-Dist: keyring (==23.0.1)
Requires-Dist: keyrings.cryptfile (==1.3.4)
Requires-Dist: PyYAML (==5.4.1)
Requires-Dist: setproctitle (==1.2.2)
Requires-Dist: sortedcontainers (==2.4.0)
Requires-Dist: websockets (==8.1.0)
Requires-Dist: click (==7.1.2)
Requires-Dist: dnspythonchia (==2.2.0)
Requires-Dist: watchdog (==2.1.6)
Requires-Dist: nest-asyncio (==1.5.1)
Provides-Extra: dev
Requires-Dist: pytest ; extra == 'dev'
Requires-Dist: pytest-asyncio ; extra == 'dev'
Requires-Dist: flake8 ; extra == 'dev'
Requires-Dist: mypy ; extra == 'dev'
Requires-Dist: black ; extra == 'dev'
Requires-Dist: aiohttp-cors ; extra == 'dev'
Requires-Dist: ipython ; extra == 'dev'
Requires-Dist: types-setuptools ; extra == 'dev'
Provides-Extra: upnp
Requires-Dist: miniupnpc (==2.2.2) ; extra == 'upnp'
Provides-Extra: uvloop
Requires-Dist: uvloop ; extra == 'uvloop'
